gandol2_image_ocr/__init__.py
gandol2_image_ocr/cli.py
gandol2_image_ocr/ocr.py
gandol2_image_ocr_v2-2.0.1.dist-info/licenses/LICENSE
gandol2_image_ocr_v2-2.0.1.dist-info/METADATA
gandol2_image_ocr_v2-2.0.1.dist-info/WHEEL
gandol2_image_ocr_v2-2.0.1.dist-info/entry_points.txt
gandol2_image_ocr_v2-2.0.1.dist-info/top_level.txt
gandol2_image_ocr_v2-2.0.1.dist-info/RECORD
