Metadata-Version: 2.4
Name: gandol2-image-ocr-v2
Version: 2.0.1
Summary: PaddleOCR 기반의 간단한 이미지 OCR 유틸리티 (GPU/CPU 지원)
Author-email: gandol2 <sskim2333@gmail.com>
License: MIT
Project-URL: Homepage, https://github.com/gandol2/gandol2-image-ocr-v2
Project-URL: Repository, https://github.com/gandol2/gandol2-image-ocr-v2
Project-URL: Issues, https://github.com/gandol2/gandol2-image-ocr-v2/issues
Keywords: ocr,paddleocr,image,gpu,korean,text-recognition
Classifier: Programming Language :: Python :: 3
Classifier: Programming Language :: Python :: 3 :: Only
Classifier: Programming Language :: Python :: 3.12
Classifier: License :: OSI Approved :: MIT License
Classifier: Operating System :: OS Independent
Classifier: Topic :: Scientific/Engineering :: Artificial Intelligence
Requires-Python: <3.13,>=3.10
License-File: LICENSE
Requires-Dist: paddleocr>=3.2.0
Requires-Dist: paddlepaddle-gpu==3.2.0
Dynamic: license-file
